akios/__init__.py
akios/__main__.py
akios/_version.py
akios/cli/.DS_Store
akios/cli/__init__.py
akios/cli/__main__.py
akios/cli/helpers.py
akios/cli/main.py
akios/cli/commands/__init__.py
akios/cli/commands/audit.py
akios/cli/commands/clean.py
akios/cli/commands/compliance.py
akios/cli/commands/doctor.py
akios/cli/commands/files.py
akios/cli/commands/init.py
akios/cli/commands/logs.py
akios/cli/commands/output.py
akios/cli/commands/run.py
akios/cli/commands/setup.py
akios/cli/commands/status.py
akios/cli/commands/templates.py
akios/cli/commands/testing.py
akios/cli/commands/workflow.py
akios/cli/data/__init__.py
akios/cli/data/samples/__init__.py
akios/cli/data/samples/analysis_targets/sample.docx
akios/cli/data/samples/analysis_targets/sample.pdf
akios/cli/data/samples/analysis_targets/sample.txt
akios/cli/data/samples/document_examples/sample.docx
akios/cli/data/samples/document_examples/sample.pdf
akios/cli/data/samples/document_examples/sample.txt
akios/config/__init__.py
akios/config/constants.py
akios/config/defaults.py
akios/config/loader.py
akios/config/modes.py
akios/config/settings.py
akios/config/validation.py
akios/core/__init__.py
akios/core/_version.py
akios/core/audit/__init__.py
akios/core/audit/events.py
akios/core/audit/ledger.py
akios/core/audit/verifier.py
akios/core/audit/exporter/json.py
akios/core/audit/merkle/__init__.py
akios/core/audit/merkle/node.py
akios/core/audit/merkle/tree.py
akios/core/cache/manager.py
akios/core/compliance/__init__.py
akios/core/compliance/report.py
akios/core/config/first_run.py
akios/core/error/classifier.py
akios/core/performance/monitor.py
akios/core/runtime/__init__.py
akios/core/runtime/agents/__init__.py
akios/core/runtime/agents/base.py
akios/core/runtime/agents/filesystem.py
akios/core/runtime/agents/http.py
akios/core/runtime/agents/llm.py
akios/core/runtime/agents/tool_executor.py
akios/core/runtime/engine/__init__.py
akios/core/runtime/engine/engine.py
akios/core/runtime/engine/kills.py
akios-1.0.4.dist-info/licenses/DCO.md
akios-1.0.4.dist-info/licenses/LEGAL.md
akios-1.0.4.dist-info/licenses/LICENSE
akios-1.0.4.dist-info/licenses/NOTICE
akios-1.0.4.dist-info/licenses/THIRD_PARTY_LICENSES.md
akios-1.0.4.dist-info/licenses/TRADEMARKS.md
akios-1.0.4.dist-info/METADATA
akios-1.0.4.dist-info/WHEEL
akios-1.0.4.dist-info/entry_points.txt
akios-1.0.4.dist-info/top_level.txt
akios-1.0.4.dist-info/RECORD
