Metadata-Version: 2.4
Name: akios
Version: 1.0.4
Summary: AKIOS runtime for secure AI agent execution
Author-email: AKIOS Team <hello@akios.ai>
License: GPL-3.0-only
Project-URL: Homepage, https://akios.ai
Project-URL: Bug Tracker, https://github.com/akios-ai/akios/issues
Project-URL: Source, https://github.com/akios-ai/akios
Requires-Python: >=3.8
License-File: LICENSE
License-File: NOTICE
License-File: LEGAL.md
License-File: THIRD_PARTY_LICENSES.md
License-File: TRADEMARKS.md
License-File: DCO.md
Requires-Dist: pydantic[email]>=2.0.0
Requires-Dist: pydantic-settings>=2.0.0
Requires-Dist: click>=8.0.0
Requires-Dist: pyyaml>=6.0
Requires-Dist: jsonschema>=4.21.0
Requires-Dist: httpx>=0.25.0
Requires-Dist: requests>=2.25.0
Requires-Dist: cryptography>=42.0.0
Requires-Dist: psutil>=5.9.0
Requires-Dist: openai>=1.0.0
Requires-Dist: anthropic>=0.30.0
Requires-Dist: google-generativeai>=0.8.0
Requires-Dist: tiktoken>=0.5.0
Requires-Dist: protobuf>=5.29.5
Requires-Dist: PyPDF2>=3.0.0
Requires-Dist: pdfminer.six>=20231228
Requires-Dist: python-docx>=1.1.0
Provides-Extra: seccomp
Requires-Dist: seccomp>=1.0.0; extra == "seccomp"
Provides-Extra: extended
Requires-Dist: backoff>=2.2.0; extra == "extended"
Requires-Dist: aiohttp>=3.9.0; extra == "extended"
Provides-Extra: api
Requires-Dist: fastapi>=0.104.0; extra == "api"
Requires-Dist: uvicorn[standard]>=0.24.0; extra == "api"
Provides-Extra: monitoring
Requires-Dist: prometheus-client>=0.17.0; extra == "monitoring"
Provides-Extra: dev
Requires-Dist: pytest>=7.0.0; extra == "dev"
Requires-Dist: pytest-cov>=4.0.0; extra == "dev"
Requires-Dist: black>=23.0.0; extra == "dev"
Requires-Dist: isort>=5.12.0; extra == "dev"
Requires-Dist: mypy>=1.0.0; extra == "dev"
Requires-Dist: ruff>=0.1.0; extra == "dev"
Requires-Dist: pre-commit>=3.0.0; extra == "dev"
Dynamic: license-file
